ragxplorer/__init__.py
ragxplorer/constants.py
ragxplorer/projections.py
ragxplorer/query_expansion.py
ragxplorer/rag.py
ragxplorer/ragxplorer.py
ragxplorer-0.1.10.dist-info/LICENSE
ragxplorer-0.1.10.dist-info/METADATA
ragxplorer-0.1.10.dist-info/WHEEL
ragxplorer-0.1.10.dist-info/top_level.txt
ragxplorer-0.1.10.dist-info/RECORD
