Metadata-Version: 2.1
Name: ragxplorer
Version: 0.1.10
Summary: A open-source tool to to visualise your RAG documents 🔮.
Home-page: https://github.com/gabrielchua/ragxplorer
Author: Gabriel Chua
Author-email: cyzgab@gmail.com
Classifier: Programming Language :: Python :: 3
Classifier: License :: OSI Approved :: MIT License
Classifier: Operating System :: OS Independent
Requires-Python: >=3.8
License-File: LICENSE
Requires-Dist: numpy
Requires-Dist: pandas
Requires-Dist: umap-learn
Requires-Dist: sentence-transformers
Requires-Dist: plotly
Requires-Dist: tqdm
Requires-Dist: PyPDF2
Requires-Dist: langchain
Requires-Dist: chromadb
Requires-Dist: openai
Requires-Dist: pydantic
